{
	"info": {
		"_postman_id": "81f6ef09-e555-4a30-95c3-7f86ad671f42",
		"name": "Library API",
		"schema": "https://schema.getpostman.com/json/collection/v2.1.0/collection.json",
		"_exporter_id": "23612952"
	},
	"item": [
		{
			"name": "Add Book",
			"request": {
				"method": "POST",
				"header": [],
				"body": {
					"mode": "raw",
					"raw": "{\r\n\r\n\"name\":\"Learn Appium Automation with Java Script\",\r\n\"isbn\":\"kmks123\",\r\n\"aisle\":\"131319\",\r\n\"author\":\"Selvan kmk\"\r\n}\r\n \r\n",
					"options": {
						"raw": {
							"language": "json"
						}
					}
				},
				"url": {
					"raw": "http://216.10.245.166/Library/Addbook.php",
					"protocol": "http",
					"host": [
						"216",
						"10",
						"245",
						"166"
					],
					"path": [
						"Library",
						"Addbook.php"
					]
				}
			},
			"response": []
		},
		{
			"name": "Get Book",
			"request": {
				"method": "GET",
				"header": [],
				"url": {
					"raw": "http://216.10.245.166/Library/GetBook.php?AuthorName=John foe",
					"protocol": "http",
					"host": [
						"216",
						"10",
						"245",
						"166"
					],
					"path": [
						"Library",
						"GetBook.php"
					],
					"query": [
						{
							"key": "AuthorName",
							"value": "John foe"
						}
					]
				}
			},
			"response": []
		},
		{
			"name": "Get Book using ID",
			"request": {
				"method": "GET",
				"header": [],
				"url": {
					"raw": "http://216.10.245.166/Library/GetBook.php?ID=3389",
					"protocol": "http",
					"host": [
						"216",
						"10",
						"245",
						"166"
					],
					"path": [
						"Library",
						"GetBook.php"
					],
					"query": [
						{
							"key": "ID",
							"value": "3389"
						}
					]
				}
			},
			"response": []
		},
		{
			"name": "Delete Book",
			"request": {
				"method": "POST",
				"header": [],
				"body": {
					"mode": "raw",
					"raw": "{\r\n \r\n\"ID\" : \"kmks123131319\"\r\n \r\n} \r\n",
					"options": {
						"raw": {
							"language": "json"
						}
					}
				},
				"url": {
					"raw": "http://216.10.245.166/Library/DeleteBook.php",
					"protocol": "http",
					"host": [
						"216",
						"10",
						"245",
						"166"
					],
					"path": [
						"Library",
						"DeleteBook.php"
					]
				}
			},
			"response": []
		}
	]
}